pybedca/__init__.py
pybedca/client.py
pybedca/enums.py
pybedca/mcp_server.py
pybedca/models.py
pybedca/parser.py
pybedca/query.py
pybedca/values.py
pybedca-1.0.0.dist-info/METADATA
pybedca-1.0.0.dist-info/WHEEL
pybedca-1.0.0.dist-info/entry_points.txt
pybedca-1.0.0.dist-info/licenses/LICENSE
pybedca-1.0.0.dist-info/RECORD
