Metadata-Version: 2.4
Name: pybedca
Version: 1.0.0
Summary: Python client library to parse BEDCA API XML into Python objects.
Author-email: Lázaro Candea <lazaro@candea.es>
License: MIT
License-File: LICENSE
Requires-Python: >=3.12
Requires-Dist: httpx>=0.28.1
Requires-Dist: mcp[cli]>=1.16.0
